src/main_control_unit.sv
module main_control_unit (
    input  logic [6:0]  opcode,
    output logic        reg_write_enable,
    output logic        mem_read_enable,
    output logic        mem_write_enable,
    output logic        mem_to_reg,
    output logic        branch_enable,
    output logic        jump_enable,
    output logic [1:0] next_pc_select
);

  import riscv_defines::*;

  always_comb begin
    reg_write_enable = 1'b0;
    mem_read_enable  = 1'b0;
    mem_write_enable = 1'b0;
    mem_to_reg       = 1'b0;
    branch_enable    = 1'b0;
    jump_enable      = 1'b0;
    next_pc_select   = NEXT_PC_PC_PLUS_4;

    case (opcode)
      OPCODE_R_TYPE: begin
        reg_write_enable = 1'b1;
        mem_to_reg       = 1'b0;
      end
      OPCODE_I_TYPE_ALU: begin
        reg_write_enable = 1'b1;
        mem_to_reg       = 1'b0;
      end
      OPCODE_I_TYPE_LOAD: begin
        reg_write_enable = 1'b1;
        mem_read_enable  = 1'b1;
        mem_to_reg       = 1'b1;
      end
      OPCODE_S_TYPE: begin
        mem_write_enable = 1'b1;
      end
      OPCODE_B_TYPE: begin
        branch_enable    = 1'b1;
        next_pc_select   = NEXT_PC_BRANCH_JUMP_TARGET;
      end
      OPCODE_U_TYPE_LUI: begin
        reg_write_enable = 1'b1;
        mem_to_reg       = 1'b0;
      end
      OPCODE_U_TYPE_AUIPC: begin
        reg_write_enable = 1'b1;
        mem_to_reg       = 1'b0;
      end
      OPCODE_J_TYPE_JAL: begin
        reg_write_enable = 1'b1;
        jump_enable      = 1'b1;
        next_pc_select   = NEXT_PC_BRANCH_JUMP_TARGET;
      end
      OPCODE_I_TYPE_JALR: begin
        reg_write_enable = 1'b1;
        jump_enable      = 1'b1;
        next_pc_select   = NEXT_PC_JALR_TARGET;
      end
      default: begin
      end
    endcase
  end

endmodule

src/riscv_defines.sv
package riscv_defines;

  localparam [6:0] OPCODE_R_TYPE        = 7'b0110011;
  localparam [6:0] OPCODE_I_TYPE_ALU    = 7'b0010011;
  localparam [6:0] OPCODE_I_TYPE_LOAD   = 7'b0000011;
  localparam [6:0] OPCODE_S_TYPE        = 7'b0100011;
  localparam [6:0] OPCODE_B_TYPE        = 7'b1100011;
  localparam [6:0] OPCODE_U_TYPE_LUI    = 7'b0110111;
  localparam [6:0] OPCODE_U_TYPE_AUIPC  = 7'b0010111;
  localparam [6:0] OPCODE_J_TYPE_JAL    = 7'b1101111;
  localparam [6:0] OPCODE_I_TYPE_JALR   = 7'b1100111;

  localparam [2:0] FUNCT3_ADD_SUB       = 3'b000;
  localparam [2:0] FUNCT3_SLL           = 3'b001;
  localparam [2:0] FUNCT3_SLT           = 3'b010;
  localparam [2:0] FUNCT3_SLTU          = 3'b011;
  localparam [2:0] FUNCT3_XOR           = 3'b100;
  localparam [2:0] FUNCT3_SR_AR         = 3'b101;
  localparam [2:0] FUNCT3_OR            = 3'b110;
  localparam [2:0] FUNCT3_AND           = 3'b111;

  localparam [6:0] FUNCT7_ADD_SLL_SRL_OR_AND_XOR_SLT_SLTU = 7'b0000000;
  localparam [6:0] FUNCT7_SUB_SRA                         = 7'b0100000;

  localparam [3:0] ALU_ADD = 4'b0000;
  localparam [3:0] ALU_SUB = 4'b0001;
  localparam [3:0] ALU_AND = 4'b0010;
  localparam [3:0] ALU_OR  = 4'b0011;
  localparam [3:0] ALU_XOR = 4'b0100;
  localparam [3:0] ALU_SLL = 4'b0101;
  localparam [3:0] ALU_SRL = 4'b0110;
  localparam [3:0] ALU_SRA = 4'b0111;
  localparam [3:0] ALU_SLT = 4'b1000;
  localparam [3:0] ALU_SLTU = 4'b1001;
  localparam [3:0] ALU_PASS_B = 4'b1111;

  localparam [1:0] NEXT_PC_PC_PLUS_4 = 2'b00;
  localparam [1:0] NEXT_PC_BRANCH_JUMP_TARGET = 2'b01;
  localparam [1:0] NEXT_PC_JALR_TARGET = 2'b10;

endpackage

src/alu_control_unit.sv
//`include "riscv_defines.sv"

module alu_control_unit (
    input  logic [6:0]  opcode,
    input  logic [2:0]  funct3,
    input  logic [6:0]  funct7,
    output logic [3:0] alu_control
);

  import riscv_defines::*;

  always_comb begin
    alu_control = ALU_ADD;

    case (opcode)
      OPCODE_R_TYPE: begin
        case (funct3)
          FUNCT3_ADD_SUB: alu_control = (funct7 == FUNCT7_SUB_SRA) ? ALU_SUB : ALU_ADD;
          FUNCT3_SLL:     alu_control = ALU_SLL;
          FUNCT3_SLT:     alu_control = ALU_SLT;
          FUNCT3_SLTU:    alu_control = ALU_SLTU;
          FUNCT3_XOR:     alu_control = ALU_XOR;
          FUNCT3_SR_AR:   alu_control = (funct7 == FUNCT7_SUB_SRA) ? ALU_SRA : ALU_SRL;
          FUNCT3_OR:      alu_control = ALU_OR;
          FUNCT3_AND:     alu_control = ALU_AND;
          default:        alu_control = ALU_ADD;
        endcase
      end
      OPCODE_I_TYPE_ALU: begin
        case (funct3)
          FUNCT3_ADD_SUB: alu_control = ALU_ADD;
          FUNCT3_SLL:     alu_control = ALU_SLL;
          FUNCT3_SLT:     alu_control = ALU_SLT;
          FUNCT3_SLTU:    alu_control = ALU_SLTU;
          FUNCT3_XOR:     alu_control = ALU_XOR;
          FUNCT3_SR_AR:   alu_control = (funct7 == FUNCT7_SUB_SRA) ? ALU_SRA : ALU_SRL;
          FUNCT3_OR:      alu_control = ALU_OR;
          FUNCT3_AND:     alu_control = ALU_AND;
          default:        alu_control = ALU_ADD;
        endcase
      end
      OPCODE_I_TYPE_LOAD, OPCODE_S_TYPE, OPCODE_B_TYPE,
      OPCODE_U_TYPE_AUIPC, OPCODE_J_TYPE_JAL, OPCODE_I_TYPE_JALR:
        alu_control = ALU_ADD;
      OPCODE_U_TYPE_LUI:
        alu_control = ALU_PASS_B;
      default:
        alu_control = ALU_ADD;
    endcase
  end

endmodule

src/immediate_generator.sv
module immediate_generator (
    input  logic [31:0] instruction,
    input  logic [6:0]  opcode,
    output logic [31:0] immediate
);

import riscv_defines::*;

  always_comb begin
    immediate = 32'b0;
    
    case (opcode)
      OPCODE_I_TYPE_ALU, OPCODE_I_TYPE_LOAD, OPCODE_I_TYPE_JALR: begin
        immediate = {{20{instruction[31]}}, instruction[31:20]};
      end
      OPCODE_S_TYPE: begin
immediate = {{20{instruction[31]}}, instruction[31:25], instruction[11:7]};
      end
      OPCODE_B_TYPE: begin
        immediate = {{19{instruction[31]}},
                     instruction[31],
                     instruction[7],
                     instruction[30:25],
                     instruction[11:8],
                     1'b0};
      end
      OPCODE_U_TYPE_LUI, OPCODE_U_TYPE_AUIPC: begin
        immediate = {instruction[31:12], 12'b0};
      end
      OPCODE_J_TYPE_JAL: begin
        immediate = {{11{instruction[31]}},
                     instruction[31],
                     instruction[19:12],
                     instruction[20],
                     instruction[30:21],
                     1'b0};
      end
      default: immediate = 32'b0;
    endcase
  end

endmodule

src/riscv_decoder.sv
module riscv_decoder (
    input  logic [31:0] instruction,
    input  logic [31:0] reg_read_data1,
    input  logic [31:0] reg_read_data2,
    input  logic [31:0] pc,

    output logic [31:0] alu_operand_a,
    output logic [31:0] alu_operand_b,
    output logic [3:0] alu_control,
    output logic        reg_write_enable,
    output logic [4:0]  reg_write_dest,
    output logic        mem_read_enable,
    output logic        mem_write_enable,
    output logic        mem_to_reg,
    output logic        branch_enable,
    output logic        jump_enable,
    output logic [1:0] next_pc_select
);

  import riscv_defines::*;

  logic [6:0] opcode;
  logic [4:0] rd;
  logic [2:0] funct3;
  logic [4:0] rs1;
  logic [4:0] rs2;
  logic [6:0] funct7;

  logic [31:0] immediate_val;

  assign opcode   = instruction[6:0];
  assign rd       = instruction[11:7];
  assign funct3   = instruction[14:12];
  assign rs1      = instruction[19:15];
  assign rs2      = instruction[24:20];
  assign funct7   = instruction[31:25];

  assign reg_write_dest = rd;

  immediate_generator i_gen (
      .instruction (instruction),
      .opcode      (opcode),
      .immediate   (immediate_val)
  );

  assign alu_operand_a = (opcode == OPCODE_U_TYPE_AUIPC) ? pc : reg_read_data1;

  logic select_imm_for_alu_b;
  always_comb begin
    case (opcode)
      OPCODE_R_TYPE:           select_imm_for_alu_b = 1'b0;
      OPCODE_I_TYPE_ALU:       select_imm_for_alu_b = 1'b1;
      OPCODE_I_TYPE_LOAD:      select_imm_for_alu_b = 1'b1;
      OPCODE_S_TYPE:           select_imm_for_alu_b = 1'b1;
      OPCODE_B_TYPE:           select_imm_for_alu_b = 1'b1;
      OPCODE_U_TYPE_LUI:       select_imm_for_alu_b = 1'b1;
      OPCODE_U_TYPE_AUIPC:     select_imm_for_alu_b = 1'b1;
      OPCODE_J_TYPE_JAL:       select_imm_for_alu_b = 1'b1;
      OPCODE_I_TYPE_JALR:      select_imm_for_alu_b = 1'b1;
      default:                 select_imm_for_alu_b = 1'b0;
    endcase
  end

  assign alu_operand_b = select_imm_for_alu_b ? immediate_val : reg_read_data2;


  alu_control_unit alu_ctrl (
      .opcode    (opcode),
      .funct3    (funct3),
      .funct7    (funct7),
      .alu_control (alu_control)
  );

  main_control_unit main_ctrl (
      .opcode             (opcode),
      .reg_write_enable   (reg_write_enable),
      .mem_read_enable    (mem_read_enable),
      .mem_write_enable   (mem_write_enable),
      .mem_to_reg         (mem_to_reg),
      .branch_enable      (branch_enable),
      .jump_enable        (jump_enable),
      .next_pc_select     (next_pc_select)
  );

endmodule

src/riscv_decoder_tb.sv
import riscv_defines::*;

module riscv_decoder_tb;

  logic [31:0] instruction;
  logic [31:0] reg_read_data1;
  logic [31:0] reg_read_data2;
  logic [31:0] pc;

  logic [31:0] alu_operand_a;
  logic [31:0] alu_operand_b;
  logic [3:0]  alu_control;
  logic        reg_write_enable;
  logic [4:0]  reg_write_dest;
  logic        mem_read_enable;
  logic        mem_write_enable;
  logic        mem_to_reg;
  logic        branch_enable;
  logic        jump_enable;
  logic [1:0]  next_pc_select;

  riscv_decoder u_decoder (
      .instruction        (instruction),
      .reg_read_data1     (reg_read_data1),
      .reg_read_data2     (reg_read_data2),
      .pc                 (pc),

      .alu_operand_a      (alu_operand_a),
      .alu_operand_b      (alu_operand_b),
      .alu_control        (alu_control),
      .reg_write_enable   (reg_write_enable),
      .reg_write_dest     (reg_write_dest),
      .mem_read_enable    (mem_read_enable),
      .mem_write_enable   (mem_write_enable),
      .mem_to_reg         (mem_to_reg),
      .branch_enable      (branch_enable),
      .jump_enable        (jump_enable),
      .next_pc_select     (next_pc_select)
  );

  initial begin
    $dumpfile("riscv_decoder.vcd");
    $dumpvars(0, riscv_decoder_tb);

    reg_read_data1 = 32'h00000100;
    reg_read_data2 = 32'h00000020;
    pc             = 32'h80000000;

    $display("--- RISC-V Decoder Testbench ---");
    $display("Initial values: RegReadData1=0x%h, RegReadData2=0x%h, PC=0x%h", reg_read_data1, reg_read_data2, pc);

    // Test 1: ADD x3, x1, x2 (R-type)
    // 0x002081B3 (binary: 0000000 00010 00001 000 00011 0110011)
    instruction = 32'h002081B3;
    #10;
    $display("\nTest 1: ADD x3, x1, x2 (0x%h)", instruction);
    $display("  ALU_OperandA = 0x%h, ALU_OperandB = 0x%h", alu_operand_a, alu_operand_b);
    $display("  ALU_Control = 0x%h", alu_control);
    $display("  RegWriteEnable = %b, RegWriteDest = x%d", reg_write_enable, reg_write_dest);
    $display("  MemReadEnable = %b, MemWriteEnable = %b, MemToReg = %b", mem_read_enable, mem_write_enable, mem_to_reg);
    $display("  BranchEnable = %b, JumpEnable = %b, NextPCSelect = 0x%h", branch_enable, jump_enable, next_pc_select); // 16進数で表示

    // Test 2: ADDI x4, x1, 10 (I-type ALU)
    // 0x00A08213 (binary: 000000001010 00001 000 00100 0010011)
    instruction = 32'h00A08213;
    #10;
    $display("\nTest 2: ADDI x4, x1, 10 (0x%h)", instruction);
    $display("  ALU_OperandA = 0x%h, ALU_OperandB = 0x%h", alu_operand_a, alu_operand_b);
    $display("  ALU_Control = 0x%h", alu_control);
    $display("  RegWriteEnable = %b, RegWriteDest = x%d", reg_write_enable, reg_write_dest);
    $display("  MemReadEnable = %b, MemWriteEnable = %b, MemToReg = %b", mem_read_enable, mem_write_enable, mem_to_reg);
    $display("  BranchEnable = %b, JumpEnable = %b, NextPCSelect = 0x%h", branch_enable, jump_enable, next_pc_select);

    // Test 3: LW x5, 4(x1) (I-type LOAD)
    // 0x0040A283
    instruction = 32'h0040A283;
    #10;
    $display("\nTest 3: LW x5, 4(x1) (0x%h)", instruction);
    $display("  ALU_OperandA = 0x%h, ALU_OperandB = 0x%h", alu_operand_a, alu_operand_b);
    $display("  ALU_Control = 0x%h", alu_control);
    $display("  RegWriteEnable = %b, RegWriteDest = x%d", reg_write_enable, reg_write_dest);
    $display("  MemReadEnable = %b, MemWriteEnable = %b, MemToReg = %b", mem_read_enable, mem_write_enable, mem_to_reg);
    $display("  BranchEnable = %b, JumpEnable = %b, NextPCSelect = 0x%h", branch_enable, jump_enable, next_pc_select);

    // Test 4: SW x2, 8(x1) (S-type)
    // 0x00212423
    instruction = 32'h00212423;
    #10;
    $display("\nTest 4: SW x2, 8(x1) (0x%h)", instruction);
    $display("  ALU_OperandA = 0x%h, ALU_OperandB = 0x%h", alu_operand_a, alu_operand_b);
    $display("  ALU_Control = 0x%h", alu_control);
    $display("  RegWriteEnable = %b, RegWriteDest = x%d", reg_write_enable, reg_write_dest);
    $display("  MemReadEnable = %b, MemWriteEnable = %b, MemToReg = %b", mem_read_enable, mem_write_enable, mem_to_reg);
    $display("  BranchEnable = %b, JumpEnable = %b, NextPCSelect = 0x%h", branch_enable, jump_enable, next_pc_select);

    // Test 5: BEQ x1, x2, 12 (B-type)
    // 0x00C08663
    instruction = 32'h00C08663;
    #10;
    $display("\nTest 5: BEQ x1, x2, 12 (0x%h)", instruction);
    $display("  ALU_OperandA = 0x%h, ALU_OperandB = 0x%h", alu_operand_a, alu_operand_b);
    $display("  ALU_Control = 0x%h", alu_control);
    $display("  RegWriteEnable = %b, RegWriteDest = x%d", reg_write_enable, reg_write_dest);
    $display("  MemReadEnable = %b, MemWriteEnable = %b, MemToReg = %b", mem_read_enable, mem_write_enable, mem_to_reg);
    $display("  BranchEnable = %b, JumpEnable = %b, NextPCSelect = 0x%h", branch_enable, jump_enable, next_pc_select);

    // Test 6: JAL x6, 20 (J-type)
    // 0x0140036F
    instruction = 32'h0140036F;
    #10;
    $display("\nTest 6: JAL x6, 20 (0x%h)", instruction);
    $display("  ALU_OperandA = 0x%h, ALU_OperandB = 0x%h", alu_operand_a, alu_operand_b);
    $display("  ALU_Control = 0x%h", alu_control);
    $display("  RegWriteEnable = %b, RegWriteDest = x%d", reg_write_enable, reg_write_dest);
    $display("  MemReadEnable = %b, MemWriteEnable = %b, MemToReg = %b", mem_read_enable, mem_write_enable, mem_to_reg);
    $display("  BranchEnable = %b, JumpEnable = %b, NextPCSelect = 0x%h", branch_enable, jump_enable, next_pc_select);

    // Test 7: LUI x11, 0x12345 (U-type)
    // 0x012345B7
    instruction = 32'h012345B7;
    #10;
    $display("\nTest 7: LUI x11, 0x12345 (0x%h)", instruction);
    $display("  ALU_OperandA = 0x%h, ALU_OperandB = 0x%h", alu_operand_a, alu_operand_b);
    $display("  ALU_Control = 0x%h", alu_control);
    $display("  RegWriteEnable = %b, RegWriteDest = x%d", reg_write_enable, reg_write_dest);
    $display("  MemReadEnable = %b, MemWriteEnable = %b, MemToReg = %b", mem_read_enable, mem_write_enable, mem_to_reg);
    $display("  BranchEnable = %b, JumpEnable = %b, NextPCSelect = 0x%h", branch_enable, jump_enable, next_pc_select);

    // Test 8: AUIPC x29, 0xABCDE (U-type)
    // 0x0ABCDE97
    instruction = 32'h0ABCDE97;
    #10;
    $display("\nTest 8: AUIPC x29, 0xABCDE (0x%h)", instruction);
    $display("  ALU_OperandA = 0x%h, ALU_OperandB = 0x%h", alu_operand_a, alu_operand_b);
    $display("  ALU_Control = 0x%h", alu_control);
    $display("  RegWriteEnable = %b, RegWriteDest = x%d", reg_write_enable, reg_write_dest);
    $display("  MemReadEnable = %b, MemWriteEnable = %b, MemToReg = %b", mem_read_enable, mem_write_enable, mem_to_reg);
    $display("  BranchEnable = %b, JumpEnable = %b, NextPCSelect = 0x%h", branch_enable, jump_enable, next_pc_select);

    $finish;

  end

endmodule

riscv_decoder.vcd
$date
	Tue Jul 29 21:16:50 2025
$end
$version
	Icarus Verilog
$end
$timescale
	1s
$end
$scope module riscv_decoder_tb $end
$var wire 1 ! reg_write_enable $end
$var wire 5 " reg_write_dest [4:0] $end
$var wire 2 # next_pc_select [1:0] $end
$var wire 1 $ mem_write_enable $end
$var wire 1 % mem_to_reg $end
$var wire 1 & mem_read_enable $end
$var wire 1 ' jump_enable $end
$var wire 1 ( branch_enable $end
$var wire 32 ) alu_operand_b [31:0] $end
$var wire 32 * alu_operand_a [31:0] $end
$var wire 4 + alu_control [3:0] $end
$var reg 32 , instruction [31:0] $end
$var reg 32 - pc [31:0] $end
$var reg 32 . reg_read_data1 [31:0] $end
$var reg 32 / reg_read_data2 [31:0] $end
$scope module u_decoder $end
$var wire 32 0 instruction [31:0] $end
$var wire 32 1 pc [31:0] $end
$var wire 32 2 reg_read_data1 [31:0] $end
$var wire 32 3 reg_read_data2 [31:0] $end
$var wire 5 4 reg_write_dest [4:0] $end
$var wire 5 5 rs2 [4:0] $end
$var wire 5 6 rs1 [4:0] $end
$var wire 1 ! reg_write_enable $end
$var wire 5 7 rd [4:0] $end
$var wire 7 8 opcode [6:0] $end
$var wire 2 9 next_pc_select [1:0] $end
$var wire 1 $ mem_write_enable $end
$var wire 1 % mem_to_reg $end
$var wire 1 & mem_read_enable $end
$var wire 1 ' jump_enable $end
$var wire 32 : immediate_val [31:0] $end
$var wire 7 ; funct7 [6:0] $end
$var wire 3 < funct3 [2:0] $end
$var wire 1 ( branch_enable $end
$var wire 32 = alu_operand_b [31:0] $end
$var wire 32 > alu_operand_a [31:0] $end
$var wire 4 ? alu_control [3:0] $end
$var reg 1 @ select_imm_for_alu_b $end
$scope module alu_ctrl $end
$var wire 3 A funct3 [2:0] $end
$var wire 7 B funct7 [6:0] $end
$var wire 7 C opcode [6:0] $end
$var reg 4 D alu_control [3:0] $end
$upscope $end
$scope module i_gen $end
$var wire 32 E instruction [31:0] $end
$var wire 7 F opcode [6:0] $end
$var reg 32 G immediate [31:0] $end
$upscope $end
$scope module main_ctrl $end
$var wire 7 H opcode [6:0] $end
$var reg 1 ( branch_enable $end
$var reg 1 ' jump_enable $end
$var reg 1 & mem_read_enable $end
$var reg 1 % mem_to_reg $end
$var reg 1 $ mem_write_enable $end
$var reg 2 I next_pc_select [1:0] $end
$var reg 1 ! reg_write_enable $end
$upscope $end
$upscope $end
$upscope $end
$enddefinitions $end
$comment Show the parameter values. $end
$dumpall
$end
#0
$dumpvars
b0 I
b110011 H
b0 G
b110011 F
b1000001000000110110011 E
b0 D
b110011 C
b0 B
b0 A
0@
b0 ?
b100000000 >
b100000 =
b0 <
b0 ;
b0 :
b0 9
b110011 8
b11 7
b1 6
b10 5
b11 4
b100000 3
b100000000 2
b10000000000000000000000000000000 1
b1000001000000110110011 0
b100000 /
b100000000 .
b10000000000000000000000000000000 -
b1000001000000110110011 ,
b0 +
b100000000 *
b100000 )
0(
0'
0&
0%
0$
b0 #
b11 "
1!
$end
#10
b1010 )
b1010 =
b1010 :
b1010 G
1!
1@
b10011 8
b10011 C
b10011 F
b10011 H
b100 "
b100 4
b100 7
b1010 5
b101000001000001000010011 ,
b101000001000001000010011 0
b101000001000001000010011 E
#20
1%
1&
1!
b100 )
b100 =
b11 8
b11 C
b11 F
b11 H
b101 "
b101 4
b101 7
b10 <
b10 A
b100 5
b100 :
b100 G
b10000001010001010000011 ,
b10000001010001010000011 0
b10000001010001010000011 E
#30
1$
0%
0&
0!
b1000 )
b1000 =
b100011 8
b100011 C
b100011 F
b100011 H
b1000 "
b1000 4
b1000 7
b10 6
b10 5
b1000 :
b1000 G
b1000010010010000100011 ,
b1000010010010000100011 0
b1000010010010000100011 E
#40
b1 #
b1 9
b1 I
1(
0$
b1100 )
b1100 =
b1100011 8
b1100011 C
b1100011 F
b1100011 H
b1100 "
b1100 4
b1100 7
b0 <
b0 A
b1 6
b1100 5
b1100 :
b1100 G
b110000001000011001100011 ,
b110000001000011001100011 0
b110000001000011001100011 E
#50
1'
1!
b1 #
b1 9
b1 I
0(
b10100 )
b10100 =
b1101111 8
b1101111 C
b1101111 F
b1101111 H
b110 "
b110 4
b110 7
b0 6
b10100 5
b10100 :
b10100 G
b1010000000000001101101111 ,
b1010000000000001101101111 0
b1010000000000001101101111 E
#60
b0 #
b0 9
b0 I
0'
1!
b1111 +
b1111 ?
b1111 D
b1001000110100000000000000 )
b1001000110100000000000000 =
b110111 8
b110111 C
b110111 F
b110111 H
b1011 "
b1011 4
b1011 7
b100 <
b100 A
b110 6
b10010 5
b1001000110100000000000000 :
b1001000110100000000000000 G
b1001000110100010110110111 ,
b1001000110100010110110111 0
b1001000110100010110110111 E
#70
b10000000000000000000000000000000 *
b10000000000000000000000000000000 >
1!
b0 +
b0 ?
b0 D
b1010101111001101000000000000 )
b1010101111001101000000000000 =
b10111 8
b10111 C
b10111 F
b10111 H
b11101 "
b11101 4
b11101 7
b101 <
b101 A
b11001 6
b1011 5
b101 ;
b101 B
b1010101111001101000000000000 :
b1010101111001101000000000000 G
b1010101111001101111010010111 ,
b1010101111001101111010010111 0
b1010101111001101111010010111 E
